odoo/addons/hr_expense_advance_overdue_reminder/README.rst
odoo/addons/hr_expense_advance_overdue_reminder/__init__.py
odoo/addons/hr_expense_advance_overdue_reminder/__manifest__.py
odoo/addons/hr_expense_advance_overdue_reminder/data/mail_template.xml
odoo/addons/hr_expense_advance_overdue_reminder/data/sequence_data.xml
odoo/addons/hr_expense_advance_overdue_reminder/i18n/es.po
odoo/addons/hr_expense_advance_overdue_reminder/i18n/hr_expense_advance_overdue_reminder.pot
odoo/addons/hr_expense_advance_overdue_reminder/i18n/it.po
odoo/addons/hr_expense_advance_overdue_reminder/models/__init__.py
odoo/addons/hr_expense_advance_overdue_reminder/models/base_reminder_mixin.py
odoo/addons/hr_expense_advance_overdue_reminder/models/hr_advance_overdue_reminder.py
odoo/addons/hr_expense_advance_overdue_reminder/models/hr_expense_sheet.py
odoo/addons/hr_expense_advance_overdue_reminder/models/reminder_definition.py
odoo/addons/hr_expense_advance_overdue_reminder/readme/CONFIGURE.rst
odoo/addons/hr_expense_advance_overdue_reminder/readme/CONTRIBUTORS.rst
odoo/addons/hr_expense_advance_overdue_reminder/readme/DESCRIPTION.rst
odoo/addons/hr_expense_advance_overdue_reminder/readme/USAGE.rst
odoo/addons/hr_expense_advance_overdue_reminder/security/ir.model.access.csv
odoo/addons/hr_expense_advance_overdue_reminder/static/description/icon.png
odoo/addons/hr_expense_advance_overdue_reminder/static/description/index.html
odoo/addons/hr_expense_advance_overdue_reminder/tests/__init__.py
odoo/addons/hr_expense_advance_overdue_reminder/tests/test_hr_expense_advance_overdue_reminder.py
odoo/addons/hr_expense_advance_overdue_reminder/views/hr_advance_overdue_view.xml
odoo/addons/hr_expense_advance_overdue_reminder/views/hr_expense_views.xml
odoo/addons/hr_expense_advance_overdue_reminder/views/reminder_definition_view.xml
odoo/addons/hr_expense_advance_overdue_reminder/wizard/__init__.py
odoo/addons/hr_expense_advance_overdue_reminder/wizard/hr_advance_overdue_reminder_wizard.py
odoo_addon_hr_expense_advance_overdue_reminder-15.0.1.0.0.11.dist-info/METADATA
odoo_addon_hr_expense_advance_overdue_reminder-15.0.1.0.0.11.dist-info/WHEEL
odoo_addon_hr_expense_advance_overdue_reminder-15.0.1.0.0.11.dist-info/top_level.txt
odoo_addon_hr_expense_advance_overdue_reminder-15.0.1.0.0.11.dist-info/RECORD
