Metadata-Version: 2.1
Name: odoo-addon-hr_expense_advance_overdue_reminder
Version: 15.0.1.0.0.11
Summary: Simple mail overdue employee advance reminder
Home-page: https://github.com/OCA/hr-expense
Author: Ecosoft, Odoo Community Association (OCA)
Author-email: support@odoo-community.org
License: AGPL-3
Classifier: Programming Language :: Python
Classifier: Framework :: Odoo
Classifier: Framework :: Odoo :: 15.0
Classifier: License :: OSI Approved :: GNU Affero General Public License v3
Requires-Python: >=3.8
Requires-Dist: odoo-addon-hr-expense-advance-clearing-sequence<15.1dev,>=15.0dev
Requires-Dist: odoo<15.1dev,>=15.0a
